algeria/__init__.py
algeria/ccp.py
algeria-0.2.0.dist-info/METADATA
algeria-0.2.0.dist-info/WHEEL
algeria-0.2.0.dist-info/top_level.txt
algeria-0.2.0.dist-info/RECORD
