Metadata-Version: 2.1
Name: algeria
Version: 0.2.0
Summary: Python library which gives you a (clé) and (rip) of a given (ccp) CCP number account, additional features may be added to the library in the future
Home-page: https://github.com/mouh2020/algeria
Author: Mohammed BADI
Author-email: badi.mohammed@univ-oran2.dz
License: UNKNOWN
Platform: UNKNOWN
Classifier: Development Status :: 3 - Alpha
Classifier: License :: OSI Approved :: MIT License
Classifier: Programming Language :: Python :: 3
Classifier: Programming Language :: Python :: 3.6
Classifier: Programming Language :: Python :: 3.7
Classifier: Programming Language :: Python :: 3.8
Classifier: Programming Language :: Python :: 3.9
Requires-Python: >=3.6
